Verilog/t06_second_largest/second_largest1.v


module second_largest #(parameter WIDTH=8) (
	input wire clk,
	input wire resetn,
	input wire [WIDTH-1:0] din,
	output reg [WIDTH-1:0] dout	
);

reg [WIDTH-1:0] lar, sec;


always @ (posedge clk) begin
	if (!resetn) begin
		lar<=0;
		sec<=0;
		dout<=0;
	end else begin

		if (din>=lar) begin
			sec<=lar;
			lar<=din;
		end else if (din<lar && din>sec) begin
			sec<=din;
		end
	dout<=sec;
	end


end






endmodule

Verilog/t06_second_largest/test.v


`timescale 1ns/1ps;



module test();

parameter WIDTH =16;

reg 			 clk;
reg 			 resetn;
reg  [WIDTH-1:0] din;
wire [WIDTH-1:0] dout;


second_largest #(WIDTH) sl(
	.clk(clk),
	.din(din),
	.resetn(resetn),
	.dout(dout)
);



initial begin
clk=0;
forever #2 clk = ! clk;
end


initial begin
$dumpfile("wave.vcd");
$dumpvars(0,test);


resetn=0;
#4

resetn=1;
din=3;
#4;


din = 3;  #5;
$display("din= %d dout = %0d",din, dout);

din = 10; #5;
$display("din= %d dout = %0d",din, dout);

din = 2;  #5;
$display("din= %d dout = %0d",din, dout);

din = 7;  #5;
$display("din= %d dout = %0d",din, dout);

din = 20;  #5;
$display("din= %d dout = %0d",din, dout);




#10
$display("din= %d dout = %0d",din,dout);




$finish;
end




endmodule

Verilog/t06_second_largest/wave.vcd
$date
	Sun Jun 15 18:20:25 2025
$end
$version
	Icarus Verilog
$end
$timescale
	1ps
$end
$scope module test $end
$var wire 16 ! dout [15:0] $end
$var parameter 32 " WIDTH $end
$var reg 1 # clk $end
$var reg 16 $ din [15:0] $end
$var reg 1 % resetn $end
$scope module sl $end
$var wire 1 # clk $end
$var wire 16 & din [15:0] $end
$var wire 1 % resetn $end
$var parameter 32 ' WIDTH $end
$var reg 16 ( dout [15:0] $end
$var reg 16 ) lar [15:0] $end
$var reg 16 * sec [15:0] $end
$upscope $end
$upscope $end
$enddefinitions $end
$comment Show the parameter values. $end
$dumpall
b10000 '
b10000 "
$end
#0
$dumpvars
bx *
bx )
bx (
bx &
0%
bx $
0#
bx !
$end
#2000
b0 !
b0 (
b0 *
b0 )
1#
#4000
0#
b11 $
b11 &
1%
#6000
b11 )
1#
#8000
0#
#10000
b11 *
1#
#12000
0#
#13000
b1010 $
b1010 &
#14000
b11 !
b11 (
b1010 )
1#
#16000
0#
#18000
1#
b10 $
b10 &
#20000
0#
#22000
1#
#23000
b111 $
b111 &
#24000
0#
#26000
b111 *
1#
#28000
0#
b10100 $
b10100 &
#30000
b111 !
b111 (
b10100 )
b1010 *
1#
#32000
0#
#34000
b1010 !
b1010 (
b10100 *
1#
#36000
0#
#38000
b10100 !
b10100 (
1#
