t11_FIFO/attempt2/fifo.v


module fifo #( parameter WIDTH=8, LENGTH=10 )
(
input wire clk,
input wire rstn,
input wire w_en,
input wire r_en,
input wire [WIDTH-1:0] data_in,
output reg [WIDTH-1:0] data_out,
output wire full,
output wire empty
);


reg [WIDTH-1:0] mem [0:LENGTH-1];
reg [$clog2(WIDTH):0] counter, w_ptr, r_ptr;


//reset
always @ (posedge clk) begin
if (!rstn) begin
	data_out<=0;
	counter<=0;
	w_ptr<=0;
	r_ptr<=0;
end
end


//write
always @ (posedge clk) begin
if (w_en && !full) begin
mem[w_ptr] <= data_in;
w_ptr <= w_ptr+1;
counter <= counter+1;
end
end


always @ (posedge clk) begin
if (r_en && !empty) begin
data_out<=mem[r_ptr];
r_ptr<=r_ptr+1;
counter<=counter-1;
end
end


assign full= (counter==LENGTH);
assign empty = (counter==0);



endmodule

t11_FIFO/attempt2/test.v
module sync_fifo_TB;

	  reg clk, rst_n;
	  reg w_en, r_en;
	  reg [7:0] data_in;
	  wire [7:0] data_out;
	  wire full, empty;	  
      fifo fifo0(clk, rst_n, w_en, r_en, data_in, data_out, full, empty);

		initial clk = 0;
		always #2 clk = ~clk;
	 
	initial begin
	  clk = 0; 
	  rst_n = 0;
	  w_en = 0; 
	  r_en = 0;
	  #3 rst_n = 1;
	  repeat (2) @(posedge clk);  // Wait for 2 cycles
	  drive(20);
	  drive(40);
	  $finish;
	end

	 

	task push;
	  begin
	    if (!full) begin
	      w_en = 1;
	      data_in = $random;
	      $display("Push In: w_en=%b, r_en=%b, data_in=%h", w_en, r_en, data_in);
	      #2; w_en = 0;
	    end else begin
	      $display("FIFO Full!! Can not push data_in=%d", data_in);
	    end
	  end
	endtask


	task pop;
	  begin
	    if (!empty) begin
	      r_en = 1;
	      $display("Pop Out: w_en=%b, r_en=%b, data_out=%h", w_en, r_en, data_out);
	      #2; r_en = 0;
	    end else begin
	      $display("FIFO Empty!! Can not pop data_out");
	    end
	  end
	endtask


	  
	task drive;
	  input integer delay;
	  begin
	    w_en = 0; r_en = 0;
	    fork
	      begin
	        repeat(10) begin @(negedge clk) #1 push(); end
	        w_en = 0;
	      end
	      begin
	        #delay;
	        repeat(10) begin @(negedge clk) #1 pop(); end
	        r_en = 0;
	      end
	    join
	  end
	endtask

	  
	initial begin 
	  $dumpfile("dump.vcd"); $dumpvars;
	end


endmodule

t11_FIFO/attempt2/dump.vcd
$date
	Sat Jun  7 12:12:39 2025
$end
$version
	Icarus Verilog
$end
$timescale
	1s
$end
$scope module sync_fifo_TB $end
$var wire 1 ! full $end
$var wire 1 " empty $end
$var wire 8 # data_out [7:0] $end
$var reg 1 $ clk $end
$var reg 8 % data_in [7:0] $end
$var reg 1 & r_en $end
$var reg 1 ' rst_n $end
$var reg 1 ( w_en $end
$scope module fifo0 $end
$var wire 1 $ clk $end
$var wire 8 ) data_in [7:0] $end
$var wire 1 & r_en $end
$var wire 1 ' rstn $end
$var wire 1 ( w_en $end
$var wire 1 ! full $end
$var wire 1 " empty $end
$var parameter 32 * LENGTH $end
$var parameter 32 + WIDTH $end
$var reg 4 , counter [3:0] $end
$var reg 8 - data_out [7:0] $end
$var reg 4 . r_ptr [3:0] $end
$var reg 4 / w_ptr [3:0] $end
$upscope $end
$scope task drive $end
$var integer 32 0 delay [31:0] $end
$upscope $end
$scope task pop $end
$upscope $end
$scope task push $end
$upscope $end
$upscope $end
$enddefinitions $end
$comment Show the parameter values. $end
$dumpall
b1000 +
b1010 *
$end
#0
$dumpvars
bx 0
bx /
bx .
bx -
bx ,
bx )
0(
0'
0&
bx %
0$
bx #
x"
x!
$end
#2
b0 .
b0 /
0!
1"
b0 ,
b0 #
b0 -
1$
#3
1'
#4
0$
#6
1$
#8
0$
#10
b10100 0
1$
#12
0$
#13
b100100 %
b100100 )
1(
#14
0"
b1 ,
b1 /
1$
#15
0(
#16
0$
#17
b10000001 %
b10000001 )
1(
#18
b10 ,
b10 /
1$
#19
0(
#20
0$
#21
b1001 %
b1001 )
1(
#22
b11 ,
b11 /
1$
#23
0(
#24
0$
#25
b1100011 %
b1100011 )
1(
#26
b100 ,
b100 /
1$
#27
0(
#28
0$
#29
b1101 %
b1101 )
1(
#30
b101 ,
b101 /
1$
#31
0(
#32
0$
#33
1&
b10001101 %
b10001101 )
1(
#34
b110 /
b110 ,
b1 .
b100100 #
b100100 -
1$
#35
0&
0(
#36
0$
#37
b1100101 %
b1100101 )
1(
1&
#38
b10 .
b10000001 #
b10000001 -
b101 ,
b111 /
1$
#39
0(
0&
#40
0$
#41
1&
b10010 %
b10010 )
1(
#42
b1000 /
b110 ,
b11 .
b1001 #
b1001 -
1$
#43
0&
0(
#44
0$
#45
b1 %
b1 )
1(
1&
#46
b100 .
b1100011 #
b1100011 -
b101 ,
b1001 /
1$
#47
0(
0&
#48
0$
#49
1&
b1101 %
b1101 )
1(
#50
b1010 /
b110 ,
b101 .
b1101 #
b1101 -
1$
#51
0&
0(
#52
0$
#53
1&
#54
b101 ,
b110 .
b10001101 #
b10001101 -
1$
#55
0&
#56
0$
#57
1&
#58
b100 ,
b111 .
b1100101 #
b1100101 -
1$
#59
0&
#60
0$
#61
1&
#62
b11 ,
b1000 .
b10010 #
b10010 -
1$
#63
0&
#64
0$
#65
1&
#66
b10 ,
b1001 .
b1 #
b1 -
1$
#67
0&
#68
0$
#69
1&
#70
b1 ,
b1010 .
b1101 #
b1101 -
1$
#71
b101000 0
0&
#72
0$
#73
b1110110 %
b1110110 )
1(
#74
b10 ,
b1011 /
1$
#75
0(
#76
0$
#77
b111101 %
b111101 )
1(
#78
b11 ,
b1100 /
1$
#79
0(
#80
0$
#81
b11101101 %
b11101101 )
1(
#82
b100 ,
b1101 /
1$
#83
0(
#84
0$
#85
b10001100 %
b10001100 )
1(
#86
b101 ,
b1110 /
1$
#87
0(
#88
0$
#89
b11111001 %
b11111001 )
1(
#90
b110 ,
b1111 /
1$
#91
0(
#92
0$
#93
b11000110 %
b11000110 )
1(
#94
b111 ,
b0 /
1$
#95
0(
#96
0$
#97
b11000101 %
b11000101 )
1(
#98
b1000 ,
b1 /
1$
#99
0(
#100
0$
#101
b10101010 %
b10101010 )
1(
#102
b1001 ,
b10 /
1$
#103
0(
#104
0$
#105
b11100101 %
b11100101 )
1(
#106
1!
b1010 ,
b11 /
1$
#107
0(
#108
0$
#110
1$
#112
0$
#113
1&
#114
0!
b1001 ,
b1011 .
bx #
bx -
1$
#115
0&
#116
0$
#117
1&
#118
b1000 ,
b1100 .
1$
#119
0&
#120
0$
#121
1&
#122
b111 ,
b1101 .
1$
#123
0&
#124
0$
#125
1&
#126
b110 ,
b1110 .
1$
#127
0&
#128
0$
#129
1&
#130
b101 ,
b1111 .
1$
#131
0&
#132
0$
#133
1&
#134
b100 ,
b0 .
1$
#135
0&
#136
0$
#137
1&
#138
b11 ,
b1 .
b11000101 #
b11000101 -
1$
#139
0&
#140
0$
#141
1&
#142
b10 ,
b10 .
b10101010 #
b10101010 -
1$
#143
0&
#144
0$
#145
1&
#146
b1 ,
b11 .
b11100101 #
b11100101 -
1$
#147
0&
#148
0$
#149
1&
#150
1"
b0 ,
b100 .
b1100011 #
b1100011 -
1$
#151
0&
