t11_FIFO/attempt1/fifo.v


// FIFO implementation


module fifo #(	parameter DATA_W=8,
				parameter L=10,
				parameter ADD_W=$clog2(L)
			)
(
	input wire clk,
	input wire rst,

	input wire wr_en,
	input wire rd_en,
	input wire [DATA_W-1:0] din,

	output reg [DATA_W-1:0] dout,
	output wire full,
	output wire empty
);

// memory, pointers for read write and counter. 
reg [DATA_W-1:0] mem [L-1:0];
reg [ADD_W-1:0] rd_ptr, wrt_ptr;
reg [ADD_W:0] count;


always @ (posedge clk or posedge rst) begin

	if (rst) begin
		count<=0;
		wrt_ptr<=0;
		rd_ptr<=0;
	end else begin

		//write fifo
		
		if (wr_en && !full) begin
			mem[wrt_ptr] <= din;
			wrt_ptr <= wrt_ptr+1;
			count <= count + 1;
			$display("din: ",din);
			//$display("writing mem[",wrt_ptr,"]: ",din," count: ",count," empty: ",empty," full: ",full);
		end

		//read fifo
		if (rd_en && !empty) begin
			dout<=mem[rd_ptr];
			rd_ptr<=rd_ptr+1;
			count <= count - 1;
			//$display("reading mem[",rd_ptr,"]: ",dout," count: ",count," empty: ",empty," full: ",full);
		end
	
	end


end

assign full = (count  == L) ;
assign	empty = (count==0);



endmodule

t11_FIFO/attempt1/test.v


`timescale 1ns/1ps;



module test();

parameter DATA_W=8;
parameter L=3;
parameter ADD_W=$clog2(L);

reg clk;
reg rst;
reg wr_en;
reg rd_en;
reg [DATA_W-1:0] din;

wire [DATA_W-1:0] dout;
wire full;
wire empty;


fifo #(	.DATA_W(DATA_W),
		.L(L)
	) fifo0 	
(
	.clk(clk),
	.rst(rst),
	.wr_en(wr_en),
	.rd_en(rd_en),
	.din(din),
	.dout(dout),
	.full(full),
	.empty(empty)
);


initial begin
clk=0;
forever #2 clk=!clk;
end



initial begin
$dumpfile("wave.vcd");
$dumpvars(0,test);

$monitor("dout: %d",dout," full: ",full," empty: ",empty);
rst=1;  #10;
rst=0;  
rd_en=0;

//set the data before enabling the wr_en.
 wr_en=1;

//write in a bunch of files. 
din=3; #4;
din=4; #4;
din=5; #4;


wr_en=0; rd_en=1;
#20

wr_en=1; rd_en=0;
din=6; #4;
din=7; #4;

wr_en=0; rd_en=1;
#8



#100;
$finish;
end


endmodule

t11_FIFO/attempt1/wave.vcd
$date
	Sat May 31 18:37:08 2025
$end
$version
	Icarus Verilog
$end
$timescale
	1ps
$end
$scope module test $end
$var wire 1 ! full $end
$var wire 1 " empty $end
$var wire 8 # dout [7:0] $end
$var parameter 32 $ ADD_W $end
$var parameter 32 % DATA_W $end
$var parameter 32 & L $end
$var reg 1 ' clk $end
$var reg 8 ( din [7:0] $end
$var reg 1 ) rd_en $end
$var reg 1 * rst $end
$var reg 1 + wr_en $end
$scope module fifo0 $end
$var wire 1 ' clk $end
$var wire 8 , din [7:0] $end
$var wire 1 ) rd_en $end
$var wire 1 * rst $end
$var wire 1 + wr_en $end
$var wire 1 ! full $end
$var wire 1 " empty $end
$var parameter 32 - ADD_W $end
$var parameter 32 . DATA_W $end
$var parameter 32 / L $end
$var reg 3 0 count [2:0] $end
$var reg 8 1 dout [7:0] $end
$var reg 2 2 rd_ptr [1:0] $end
$var reg 2 3 wrt_ptr [1:0] $end
$upscope $end
$upscope $end
$enddefinitions $end
$comment Show the parameter values. $end
$dumpall
b11 /
b1000 .
b10 -
b11 &
b1000 %
b10 $
$end
#0
$dumpvars
b0 3
b0 2
bx 1
b0 0
bx ,
x+
1*
x)
bx (
0'
bx #
1"
0!
$end
#2000
1'
#4000
0'
#6000
1'
#8000
0'
#10000
0"
b1 0
b1 3
1'
b11 (
b11 ,
1+
0)
0*
#12000
0'
#14000
b10 0
b10 3
1'
b100 (
b100 ,
#16000
0'
#18000
1!
b11 0
b11 3
1'
b101 (
b101 ,
#20000
0'
#22000
0!
b10 0
b1 2
b11 #
b11 1
1'
1)
0+
#24000
0'
#26000
b1 0
b10 2
b100 #
b100 1
1'
#28000
0'
#30000
1"
b0 0
b11 2
b101 #
b101 1
1'
#32000
0'
#34000
1'
#36000
0'
#38000
1'
#40000
0'
#42000
0"
b1 0
b0 3
1'
b110 (
b110 ,
0)
1+
#44000
0'
#46000
b10 0
b1 3
1'
b111 (
b111 ,
#48000
0'
#50000
b1 0
b0 2
bx #
bx 1
1'
1)
0+
#52000
0'
#54000
1"
b0 0
b1 2
b111 #
b111 1
1'
