t8_fibonacci_gen/finobacci.v

// this is interesting because it can be implemented with a shifter.
// just a chain of flip flops that update in the right way. 


module fibonacci #(parameter W=32)
(
	input  wire  clk,
	input  wire  [W-1:0] din,
	input  wire  resetn,
	output wire  [W-1:0] dout
);


reg [W-1:0] a,b,c;


always @ (posedge clk) begin
	if (!resetn) begin
		a<=2;
		b<=1;
		c<=1;
	end else begin
		c<=b;
		b<=a;
		a<=a+b;
	end
end


assign dout = c;


endmodule

t8_fibonacci_gen/test.v

`timescale 1ns/1ps;


module test();

parameter W=16;

reg 		    clk;
reg  [W-1:0] 	din;
reg  			resetn;
wire [W-1:0] 	dout;


fibonacci #(.W(W)) fb (
	.clk(clk),
	.din(din),
	.resetn(resetn),
	.dout(dout)
);



initial begin
clk=0;
forever #2 clk=!clk;
end


initial begin
$dumpfile("wave.vcd");
$dumpvars(0,test);

resetn=1;
#4
resetn=0;
#4
resetn=1;
#4


#4 $display("dout: ",dout);

#4 $display("dout: ",dout);

#4 $display("dout: ",dout);

#4 $display("dout: ",dout);


$finish;
end


endmodule

t8_fibonacci_gen/wave.vcd
$date
	Fri May 30 16:57:26 2025
$end
$version
	Icarus Verilog
$end
$timescale
	1ps
$end
$scope module test $end
$var wire 16 ! dout [15:0] $end
$var parameter 32 " W $end
$var reg 1 # clk $end
$var reg 16 $ din [15:0] $end
$var reg 1 % resetn $end
$scope module fb $end
$var wire 1 # clk $end
$var wire 16 & din [15:0] $end
$var wire 16 ' dout [15:0] $end
$var wire 1 % resetn $end
$var parameter 32 ( W $end
$var reg 16 ) a [15:0] $end
$var reg 16 * b [15:0] $end
$var reg 16 + c [15:0] $end
$upscope $end
$upscope $end
$enddefinitions $end
$comment Show the parameter values. $end
$dumpall
b10000 (
b10000 "
$end
#0
$dumpvars
bx +
bx *
bx )
bx '
bx &
1%
bx $
0#
bx !
$end
#2000
1#
#4000
0#
0%
#6000
b1 !
b1 '
b1 +
b1 *
b10 )
1#
#8000
0#
1%
#10000
b11 )
b10 *
1#
#12000
0#
#14000
b101 )
b11 *
b10 !
b10 '
b10 +
1#
#16000
0#
#18000
b1000 )
b101 *
b11 !
b11 '
b11 +
1#
#20000
0#
#22000
b1101 )
b1000 *
b101 !
b101 '
b101 +
1#
#24000
0#
#26000
b10101 )
b1101 *
b1000 !
b1000 '
b1000 +
1#
