Verilog/t05_priority_enc/pe_4b.v


module pe_4b (
	input wire [3:0] in,
	output reg [$clog2(4)-1:0] out,
	output wire val
);


always @ (*) begin

	casex (in)
	4'b0001:	out=0;
	4'b001x:	out=1;
	4'b01xx:	out=2;
	4'b1xxx:	out=3;
	default:	out=0;
	endcase

end

assign 	val = |in;

endmodule

Verilog/t05_priority_enc/pe_8b.v



module pe_8b (
	input wire [7:0] in,
	output reg [$clog2(8)-1:0] out,
	output wire val
);

always @ (*) begin
	casex (in)
	8'b00000001:	out=0;
	8'b0000001x:	out=1;
	8'b000001xx:	out=2;
	8'b00001xxx:	out=3;
	8'b0001xxxx:	out=4;
	8'b001xxxxx:	out=5;
	8'b01xxxxxx:	out=6;
	8'b1xxxxxxx:	out=7;
	default:		out=0;
	endcase

end

assign val =|in;


endmodule

t5_priority_enc/pe_32b.v


// This is a priority encoder for 32 bit. 
// It is pipelined in 2 stages for high throughput. 
// the first stage is composed of 4 8bit encoders in parallel
// followed by one 4 bit encoder at the end. (this creates the 2 stage pipeline)

// 32 bit input priority encoder

module pe_32b (
					input wire [31:0]   		in,
					input wire 					clk,
					input wire 					rst,
					output reg 					val,
					output reg [$clog2(32):0] 	out
);

wire [3:0]	val_t;
wire [3:0]	out_t[3:0];

wire   		val_2s;

reg [3:0]   val_t_reg;
reg [2:0]   out_t_reg [3:0];
wire [1:0]  out_2s;
reg [1:0]   out_2s_reg;


// this 4 priority encoders works in parallel.
// this is the first stage of the pipeline.
// this is all combinatorial logic!!
pe_8b pe_0 (
	.in(in[31:24]),
	.val(val_t[0]),
	.out(out_t[0])
);

pe_8b pe_1 (
	.in(in[23:16]),
	.val(val_t[1]),
	.out(out_t[1])	
);

pe_8b pe_2 (
	.in(in[15:8]),
	.val(val_t[2]),
	.out(out_t[2])	
);

pe_8b pe_3 (
	.in(in[7:0]),
	.val(val_t[3]),
	.out(out_t[3])	
);


// first pipeline stage.
always @ (posedge clk or posedge rst) begin

	if (rst) begin
		val_t_reg <=0;
		out_t_reg[0] <=0;
		out_t_reg[1] <=0;
		out_t_reg[2] <=0;
		out_t_reg[3] <=0;
	end else begin
		val_t_reg[0] <= val_t[3]; out_t_reg[0] <= out_t[3];
		val_t_reg[1] <= val_t[2]; out_t_reg[1] <= out_t[2];
		val_t_reg[2] <= val_t[1]; out_t_reg[2] <= out_t[1];
		val_t_reg[3] <= val_t[0]; out_t_reg[3] <= out_t[0];	
		$display("1st pipe val: %b  ",val_t_reg);			
	end
end

//another stage of combinatorial logic. 
pe_4b pe_4(
	.in(val_t_reg),
	.val(val_2s),
	.out(out_2s)
);


// second stage of the pipeline
// latch it to the output register.
// 
always @ (posedge clk or posedge rst) begin

	if (rst) begin
		out<=0;
		val<=0;
	end
	else begin
		//{ winning_group_2_bits , winning_bit_in_group }
		out<= {out_2s,out_t_reg[out_2s]};
		val<= val_2s;
	end


end




endmodule

t5_priority_enc/test32b.v


`timescale 1ns/1ps;


module test();

localparam w=32;

reg 				clk;
reg [w-1:0]			in;
reg 				rst;
wire 				val;
wire [$clog2(w):0]	out;


pe_32b pe32 (
	.in(in),
	.clk(clk),
	.rst(rst),
	.val(val),
	.out(out)	
);


initial begin
clk=0;
forever #2 clk=!clk;
end


initial begin 
$dumpfile("wave.vcd");
$dumpvars(0,test);


$monitor("monitor. time: %0t rst: %d val: %d out: %d",$time,rst,val,out);

rst=1;
#4

rst=0;
in=32'b00000000000000000000000000000001;
#4

in=32'b00000000000000000000000000000010;
#4

in=32'b00000000000000000000000000001000;
#4

in=32'b00000000000000000000000000010000;
#4

in=32'b00000000000000000000000000100000;
#4

in=32'b00000000000000000000000001000000;
#4
in=32'b00000000000000000000000010000000;
#4
in=32'b00000000000000000000000100000000;
#4
in=32'b00000000000000000000001000000000;
#4



in=32'b00000010010000010000001000000000;
#4


in=32'b00010001000000001000000100000000;
#4


in=32'b10000001000001000100000010000000;
#10

$finish;

end



endmodule

t5_priority_enc/wave.vcd
$date
	Sun May 25 12:20:23 2025
$end
$version
	Icarus Verilog
$end
$timescale
	1ps
$end
$scope module test $end
$var wire 1 ! val $end
$var wire 6 " out [5:0] $end
$var parameter 32 # w $end
$var reg 1 $ clk $end
$var reg 32 % in [31:0] $end
$var reg 1 & rst $end
$scope module pe32 $end
$var wire 1 $ clk $end
$var wire 32 ' in [31:0] $end
$var wire 1 & rst $end
$var wire 4 ( val_t [3:0] $end
$var wire 1 ) val_2s $end
$var wire 2 * out_2s [1:0] $end
$var reg 6 + out [5:0] $end
$var reg 1 ! val $end
$var reg 4 , val_t_reg [3:0] $end
$scope module pe_0 $end
$var wire 8 - in [7:0] $end
$var reg 4 . out [3:0] $end
$var reg 1 / val $end
$upscope $end
$scope module pe_1 $end
$var wire 8 0 in [7:0] $end
$var reg 4 1 out [3:0] $end
$var reg 1 2 val $end
$upscope $end
$scope module pe_2 $end
$var wire 8 3 in [7:0] $end
$var reg 4 4 out [3:0] $end
$var reg 1 5 val $end
$upscope $end
$scope module pe_3 $end
$var wire 8 6 in [7:0] $end
$var reg 4 7 out [3:0] $end
$var reg 1 8 val $end
$upscope $end
$scope module pe_4 $end
$var wire 4 9 in [3:0] $end
$var reg 2 : out [1:0] $end
$var reg 1 ) val $end
$upscope $end
$upscope $end
$upscope $end
$enddefinitions $end
$comment Show the parameter values. $end
$dumpall
b100000 #
$end
#0
$dumpvars
b0 :
b0 9
x8
bx 7
bx 6
x5
bx 4
bx 3
x2
bx 1
bx 0
x/
bx .
bx -
b0 ,
b0 +
b0 *
0)
bx (
bx '
1&
bx %
0$
b0 "
0!
$end
#2000
1$
#4000
b0 .
0/
b0 1
02
b0 4
05
b0 7
b1000 (
18
b0 -
b0 0
b0 3
b1 6
0$
b1 %
b1 '
0&
#6000
1)
b1 ,
b1 9
1$
#8000
b1 7
b10 6
0$
b10 %
b10 '
#10000
1!
1$
#12000
b11 7
b1000 6
0$
b1000 %
b1000 '
#14000
b1 "
b1 +
1$
#16000
b100 7
b10000 6
0$
b10000 %
b10000 '
#18000
b11 "
b11 +
1$
#20000
b101 7
b100000 6
0$
b100000 %
b100000 '
#22000
b100 "
b100 +
1$
#24000
b110 7
b1000000 6
0$
b1000000 %
b1000000 '
#26000
b101 "
b101 +
1$
#28000
b111 7
b10000000 6
0$
b10000000 %
b10000000 '
#30000
b110 "
b110 +
1$
#32000
15
b0 7
b100 (
08
b1 3
b0 6
0$
b100000000 %
b100000000 '
#34000
b1 *
b1 :
b111 "
b111 +
b10 ,
b10 9
1$
#36000
b1 4
b10 3
0$
b1000000000 %
b1000000000 '
#38000
b1000 "
b1000 +
1$
#40000
b1 .
1/
b110 1
b111 (
12
b10 -
b1000001 0
0$
b10010000010000001000000000 %
b10010000010000001000000000 '
#42000
b11 *
b11 :
b1001 "
b1001 +
b1110 ,
b1110 9
1$
#44000
b100 .
b0 1
b101 (
02
b111 4
b10001 -
b0 0
b10000001 3
0$
b10001000000001000000100000000 %
b10001000000001000000100000000 '
#46000
b1010 ,
b1010 9
b11001 "
b11001 +
1$
#48000
b111 .
b10 1
12
b110 4
b111 7
b1111 (
18
b10000001 -
b100 0
b1000000 3
b10000000 6
0$
b10000001000001000100000010000000 %
b10000001000001000100000010000000 '
#50000
b11100 "
b11100 +
b1111 ,
b1111 9
1$
#52000
0$
#54000
b11111 "
b11111 +
1$
