Verilog/t11_FIFO/fifo1.v

// this implementation uses 1 extra bit for the pointers, to 
// recognize the wrap around.


module fifo1 #(parameter W=8, L=8)(
	input wire clk, rstn,
	input wire w_en,r_en,
	input wire [W-1:0] data_in,
	output reg [W-1:0] data_out,
	output wire full , empty
);

parameter WPTR=$clog2(L);
reg [W-1:0] mem [L-1:0];
//notice that here I use one extra bit then necessary
reg [WPTR:0] w_ptr , r_ptr;
wire wrap;

always @ (posedge clk) begin

if (!rstn) begin
data_out<=0;
w_ptr<=0;
r_ptr<=0;
end

if(w_en & !full) begin
mem[w_ptr[WPTR-1:0]]<=data_in;
w_ptr<=w_ptr+1;
end

if(r_en & !empty) begin
data_out<=mem[r_ptr[WPTR-1:0]];
r_ptr<=r_ptr+1;
end

end


assign empty = (w_ptr==r_ptr);

assign wrap = w_ptr[WPTR] ^ r_ptr[WPTR];
assign full = wrap & ( w_ptr[WPTR-1:0] == r_ptr[WPTR-1:0]);

endmodule

t11_FIFO/test.v
module test;

	reg clk, rst_n;
	reg w_en, r_en;
	reg [7:0] data_in;
	wire [7:0] data_out;
	wire full, empty;	  
    fifo1 fifo(clk, rst_n, w_en, r_en, data_in, data_out, full, empty);

	initial begin
	clk = 0;
	forever #2 clk = ~clk;
	end

	//I like this a lot. 
	initial begin
	  clk   = 0; 						//reset everything
	  rst_n = 0;
	  w_en  = 0; 
	  r_en  = 0;
	  #3 rst_n = 1;	     			//deassert the reset.
	  repeat (2) @(posedge clk); 	//wait 2 clock cycles.
	  drive(20);					//start the test.
	  drive(40);					//test again
	  $finish;
	end

	 

	task push;
	  begin
	    if (!full) begin
	      w_en = 1;
	      data_in = $random;
	      $display("Push In: w_en=%b, r_en=%b, data_in=%h", w_en, r_en, data_in);
	      #2; w_en = 0;
	    end else begin
	      $display("FIFO Full!! Can not push data_in=%d", data_in);
	    end
	  end
	endtask


	task pop;
	  begin
	    if (!empty) begin
	      r_en = 1;
	      $display("Pop Out: w_en=%b, r_en=%b, data_out=%h", w_en, r_en, data_out);
	      #2; r_en = 0;
	    end else begin
	      $display("FIFO Empty!! Can not pop data_out");
	    end
	  end
	endtask

	// fork ... join in Verilog means run both branches of code 
	// in parallel (like threads).
	// the second thread is squed over a of delay from the first.
	
	  
	task drive;
	  input integer delay;
	  begin
	    w_en = 0; r_en = 0;
	    fork
	      begin
	        repeat(10) begin @(negedge clk) #1 push(); end
	      end
	      begin
	        #delay;
	        repeat(10) begin @(negedge clk) #1 pop(); end
	      end
	    join
	  end
	endtask

	  
	initial begin 
	  $dumpfile("dump.vcd"); $dumpvars;
	end


endmodule

t11_FIFO/dump.vcd
$date
	Sat Jun  7 18:49:48 2025
$end
$version
	Icarus Verilog
$end
$timescale
	1s
$end
$scope module test $end
$var wire 1 ! full $end
$var wire 1 " empty $end
$var wire 8 # data_out [7:0] $end
$var reg 1 $ clk $end
$var reg 8 % data_in [7:0] $end
$var reg 1 & r_en $end
$var reg 1 ' rst_n $end
$var reg 1 ( w_en $end
$scope module fifo $end
$var wire 1 $ clk $end
$var wire 8 ) data_in [7:0] $end
$var wire 1 ! full $end
$var wire 1 & r_en $end
$var wire 1 ' rstn $end
$var wire 1 ( w_en $end
$var wire 1 * wrap $end
$var wire 1 " empty $end
$var parameter 32 + L $end
$var parameter 32 , W $end
$var parameter 32 - WPTR $end
$var reg 8 . data_out [7:0] $end
$var reg 4 / r_ptr [3:0] $end
$var reg 4 0 w_ptr [3:0] $end
$upscope $end
$scope task drive $end
$var integer 32 1 delay [31:0] $end
$upscope $end
$scope task pop $end
$upscope $end
$scope task push $end
$upscope $end
$upscope $end
$enddefinitions $end
$comment Show the parameter values. $end
$dumpall
b11 -
b1000 ,
b1000 +
$end
#0
$dumpvars
bx 1
bx 0
bx /
bx .
x*
bx )
0(
0'
0&
bx %
0$
bx #
x"
x!
$end
#2
0!
0*
1"
b0 /
b0 0
b0 #
b0 .
1$
#3
1'
#4
0$
#6
1$
#8
0$
#10
b10100 1
1$
#12
0$
#13
b100100 %
b100100 )
1(
#14
0"
b1 0
1$
#15
0(
#16
0$
#17
b10000001 %
b10000001 )
1(
#18
b10 0
1$
#19
0(
#20
0$
#21
b1001 %
b1001 )
1(
#22
b11 0
1$
#23
0(
#24
0$
#25
b1100011 %
b1100011 )
1(
#26
b100 0
1$
#27
0(
#28
0$
#29
b1101 %
b1101 )
1(
#30
b101 0
1$
#31
0(
#32
0$
#33
1&
b10001101 %
b10001101 )
1(
#34
b1 /
b100100 #
b100100 .
b110 0
1$
#35
0&
0(
#36
0$
#37
b1100101 %
b1100101 )
1(
1&
#38
b10 /
b10000001 #
b10000001 .
b111 0
1$
#39
0(
0&
#40
0$
#41
1&
b10010 %
b10010 )
1(
#42
1*
b11 /
b1001 #
b1001 .
b1000 0
1$
#43
0&
0(
#44
0$
#45
b1 %
b1 )
1(
1&
#46
b100 /
b1100011 #
b1100011 .
b1001 0
1$
#47
0(
0&
#48
0$
#49
1&
b1101 %
b1101 )
1(
#50
b101 /
b1101 #
b1101 .
b1010 0
1$
#51
0&
0(
#52
0$
#53
1&
#54
b110 /
b10001101 #
b10001101 .
1$
#55
0&
#56
0$
#57
1&
#58
b111 /
b1100101 #
b1100101 .
1$
#59
0&
#60
0$
#61
1&
#62
0*
b1000 /
b10010 #
b10010 .
1$
#63
0&
#64
0$
#65
1&
#66
b1001 /
b1 #
b1 .
1$
#67
0&
#68
0$
#69
1&
#70
1"
b1010 /
b1101 #
b1101 .
1$
#71
b101000 1
0&
#72
0$
#73
b1110110 %
b1110110 )
1(
#74
0"
b1011 0
1$
#75
0(
#76
0$
#77
b111101 %
b111101 )
1(
#78
b1100 0
1$
#79
0(
#80
0$
#81
b11101101 %
b11101101 )
1(
#82
b1101 0
1$
#83
0(
#84
0$
#85
b10001100 %
b10001100 )
1(
#86
b1110 0
1$
#87
0(
#88
0$
#89
b11111001 %
b11111001 )
1(
#90
b1111 0
1$
#91
0(
#92
0$
#93
b11000110 %
b11000110 )
1(
#94
1*
b0 0
1$
#95
0(
#96
0$
#97
b11000101 %
b11000101 )
1(
#98
b1 0
1$
#99
0(
#100
0$
#101
b10101010 %
b10101010 )
1(
#102
1!
b10 0
1$
#103
0(
#104
0$
#106
1$
#108
0$
#110
1$
#112
0$
#113
1&
#114
0!
b1011 /
b1110110 #
b1110110 .
1$
#115
0&
#116
0$
#117
1&
#118
b1100 /
b111101 #
b111101 .
1$
#119
0&
#120
0$
#121
1&
#122
b1101 /
b11101101 #
b11101101 .
1$
#123
0&
#124
0$
#125
1&
#126
b1110 /
b10001100 #
b10001100 .
1$
#127
0&
#128
0$
#129
1&
#130
b1111 /
b11111001 #
b11111001 .
1$
#131
0&
#132
0$
#133
1&
#134
0*
b0 /
b11000110 #
b11000110 .
1$
#135
0&
#136
0$
#137
1&
#138
b1 /
b11000101 #
b11000101 .
1$
#139
0&
#140
0$
#141
1&
#142
1"
b10 /
b10101010 #
b10101010 .
1$
#143
0&
