t4/memory.v


module memory #(
	parameter w = 7,
	parameter l = 10
)
(
	input  wire	 		clk,
	input  wire 		reset,
	input  wire 		wrt_read,
	input  wire [w:0]	write,
	input  wire [3:0] 	add,
	input  wire 		enable,
	output wire [w:0] 	out
);

integer i;

reg [w:0] mem [l:0];
reg [w:0] out_reg;


assign out= out_reg;


always @ (posedge clk or posedge reset) begin
	if (reset) begin
		$display("resetting memory");
		out_reg<=0;
		for (i=0 ; i<l ; i=i+1) begin
			mem[i]<=0;	
		end
	end 
	else begin

		if (enable) begin
			if (wrt_read) begin
				mem[add]<=write;
				$display("assign. mem[%d]: %d",add,write);
			end else begin
				out_reg<= mem[add];
				$display("read. mem[%d]",mem[add]);
			end 
			
		end
	end
end



endmodule

t4/test.v


`timescale 1ns/1ps



module test;

localparam w=7;
localparam l=10;

reg 		clk;
reg 		reset;
reg 		wrt_read;
reg [w:0] 	write;
reg [3:0] 	add;
reg 		enable;
wire [w:0] 	out;


initial begin 
clk=0;
forever #2 clk = !clk;
end

// instance of memory
memory #( .w(w),
		  .l(l))
	mem0 (
	.clk(clk),
	.reset(reset),
	.wrt_read(wrt_read),
	.write(write),
	.add(add),
	.enable(enable),
	.out(out)
);

integer dl=5;

// test procedure 
initial begin 

$dumpfile("wave.vcd");
$dumpvars(0,test);


//initialize 
reset=1;
write=0;
add=0;
enable=0;
wrt_read=0;
#dl
$display("After reset asserted - out: %d", out);

reset=0;
enable=1;
wrt_read=1;
write=10;
add=0;
#dl

write=33;
add=3;
#dl



write=66;
add=5;
#dl


wrt_read=0;
add=0;
#dl 
$display("0) out: %d",out);

add=1;
#dl
$display("1) out: %d",out);


add=3;
#dl
$display("3) out: %d",out);






#10 
$finish;
end






endmodule

t4_memory/wave.vcd
$date
	Sat May 24 12:35:04 2025
$end
$version
	Icarus Verilog
$end
$timescale
	1ps
$end
$scope module test $end
$var wire 8 ! out [7:0] $end
$var parameter 32 " l $end
$var parameter 32 # w $end
$var reg 4 $ add [3:0] $end
$var reg 1 % clk $end
$var reg 1 & enable $end
$var reg 1 ' reset $end
$var reg 8 ( write [7:0] $end
$var reg 1 ) wrt_read $end
$var integer 32 * dl [31:0] $end
$scope module mem0 $end
$var wire 4 + add [3:0] $end
$var wire 1 % clk $end
$var wire 1 & enable $end
$var wire 8 , out [7:0] $end
$var wire 1 ' reset $end
$var wire 8 - write [7:0] $end
$var wire 1 ) wrt_read $end
$var parameter 32 . l $end
$var parameter 32 / w $end
$var reg 8 0 out_reg [7:0] $end
$var integer 32 1 i [31:0] $end
$upscope $end
$upscope $end
$enddefinitions $end
$comment Show the parameter values. $end
$dumpall
b111 /
b1010 .
b111 #
b1010 "
$end
#0
$dumpvars
b1010 1
b0 0
b0 -
b0 ,
b0 +
b101 *
0)
b0 (
1'
0&
0%
b0 $
b0 !
$end
#2000
b1010 1
1%
#4000
0%
#5000
b1010 (
b1010 -
1)
1&
0'
#6000
1%
#8000
0%
#10000
1%
b11 $
b11 +
b100001 (
b100001 -
#12000
0%
#14000
1%
#15000
b101 $
b101 +
b1000010 (
b1000010 -
#16000
0%
#18000
1%
#20000
0%
b0 $
b0 +
0)
#22000
b1010 !
b1010 ,
b1010 0
1%
#24000
0%
#25000
b1 $
b1 +
#26000
b0 !
b0 ,
b0 0
1%
#28000
0%
#30000
b100001 !
b100001 ,
b100001 0
1%
b11 $
b11 +
